AUTHORS.md
LICENSE.md
MANIFEST.in
README.md
setup.py
mplexporter/setup.py
mplexporter/mplexporter/__init__.py
mplexporter/mplexporter/_py3k_compat.py
mplexporter/mplexporter/exporter.py
mplexporter/mplexporter/tools.py
mplexporter/mplexporter/utils.py
mplexporter/mplexporter/renderers/__init__.py
mplexporter/mplexporter/renderers/base.py
mplexporter/mplexporter/renderers/fake_renderer.py
mplexporter/mplexporter/renderers/vega_renderer.py
mplexporter/mplexporter/renderers/vincent_renderer.py
mplexporter/mplexporter/tests/__init__.py
mplexporter/mplexporter/tests/test_basic.py
mplexporter/mplexporter/tests/test_utils.py
mplleaflet/__init__.py
mplleaflet/_display.py
mplleaflet/leaflet_renderer.py
mplleaflet/links.py
mplleaflet/maptiles.py
mplleaflet/utils.py
mplleaflet.egg-info/PKG-INFO
mplleaflet.egg-info/SOURCES.txt
mplleaflet.egg-info/dependency_links.txt
mplleaflet.egg-info/requires.txt
mplleaflet.egg-info/top_level.txt
mplleaflet/mplexporter/__init__.py
mplleaflet/mplexporter/_py3k_compat.py
mplleaflet/mplexporter/exporter.py
mplleaflet/mplexporter/tools.py
mplleaflet/mplexporter/utils.py
mplleaflet/mplexporter/renderers/__init__.py
mplleaflet/mplexporter/renderers/base.py
mplleaflet/mplexporter/renderers/fake_renderer.py
mplleaflet/mplexporter/renderers/vega_renderer.py
mplleaflet/mplexporter/renderers/vincent_renderer.py
mplleaflet/mplexporter/tests/__init__.py
mplleaflet/mplexporter/tests/test_basic.py
mplleaflet/mplexporter/tests/test_utils.py
mplleaflet/templates/__init__.py
mplleaflet/templates/base.html
mplleaflet/templates/ipynb.html