Metadata-Version: 1.1
Name: mplleaflet
Version: 0.0.4
Summary: Convert Matplotlib plots into Leaflet web maps
Home-page: http://github.com/jwass/mplleaflet
Author: Jacob Wasserman
Author-email: jwasserman@gmail.com
License: BSD 3-clause
Download-URL: http://github.com/jwass/mplleaflet
Platform: UNKNOWN
